setup.py
odoo/addons/helpdesk_automatic_stage_changes/CHANGELOG.md
odoo/addons/helpdesk_automatic_stage_changes/README.rst
odoo/addons/helpdesk_automatic_stage_changes/__init__.py
odoo/addons/helpdesk_automatic_stage_changes/__manifest__.py
odoo/addons/helpdesk_automatic_stage_changes/requirements.txt
odoo/addons/helpdesk_automatic_stage_changes/i18n/ca_ES.po
odoo/addons/helpdesk_automatic_stage_changes/i18n/en_US.po
odoo/addons/helpdesk_automatic_stage_changes/i18n/es.po
odoo/addons/helpdesk_automatic_stage_changes/models/__init__.py
odoo/addons/helpdesk_automatic_stage_changes/models/helpdesk_ticket.py
odoo/addons/helpdesk_automatic_stage_changes/models/helpdesk_ticket_stage.py
odoo/addons/helpdesk_automatic_stage_changes/models/mail_message.py
odoo/addons/helpdesk_automatic_stage_changes/static/description/icon.png
odoo/addons/helpdesk_automatic_stage_changes/tests/__init__.py
odoo/addons/helpdesk_automatic_stage_changes/tests/test_helpdesk_ticket_stage.py
odoo/addons/helpdesk_automatic_stage_changes/tests/test_mail_compose_message.py
odoo/addons/helpdesk_automatic_stage_changes/views/helpdesk_ticket_stage_view.xml
odoo/addons/helpdesk_automatic_stage_changes/views/helpdesk_ticket_view.xml
odoo/addons/helpdesk_automatic_stage_changes/wizard/__init__.py
odoo/addons/helpdesk_automatic_stage_changes/wizard/mail_compose_message.py
odoo/addons/helpdesk_automatic_stage_changes/wizard/mail_compose_message_view.xml
odoo_addon_helpdesk_automatic_stage_changes.egg-info/PKG-INFO
odoo_addon_helpdesk_automatic_stage_changes.egg-info/SOURCES.txt
odoo_addon_helpdesk_automatic_stage_changes.egg-info/dependency_links.txt
odoo_addon_helpdesk_automatic_stage_changes.egg-info/not-zip-safe
odoo_addon_helpdesk_automatic_stage_changes.egg-info/requires.txt
odoo_addon_helpdesk_automatic_stage_changes.egg-info/top_level.txt